htvalidator/__init__.py
htvalidator/install.py
htvalidator/main.py
htvalidator/shadow.py
htvalidator/validate.py
htvalidator/config/__init__.py
htvalidator/config/auth_config.py
htvalidator/config/keygen.py
htvalidator/os_utility/__init__.py
htvalidator/os_utility/crongen.py
htvalidator/os_utility/miscellanea.py
htvalidator/os_utility/os_check.py
htvalidator/os_utility/os_parser.py
htvalidator/os_utility/os_verify.py
htv-0.1.9.dist-info/LICENSE
htv-0.1.9.dist-info/METADATA
htv-0.1.9.dist-info/WHEEL
htv-0.1.9.dist-info/entry_points.txt
htv-0.1.9.dist-info/top_level.txt
htv-0.1.9.dist-info/RECORD
