Metadata-Version: 2.1
Name: htv
Version: 0.1.9
Summary: A Heat Teamplate Validator
Home-page: https://github.com/ko2-srls/HeatTemplateValidator
Author: floppino
Author-email: martina.clem@gmail.com
License: UNKNOWN
Platform: UNKNOWN
Classifier: Programming Language :: Python :: 3
Classifier: License :: OSI Approved :: GNU General Public License (GPL)
Classifier: Operating System :: OS Independent
Requires-Dist: yamllint
Requires-Dist: cryptography
Requires-Dist: PyYAML (==5.1)
Requires-Dist: keystoneauth1 (==3.14.0)
Requires-Dist: openstacksdk (==0.26.0)
Requires-Dist: python-cinderclient (==4.2.0)
Requires-Dist: python-glanceclient (==2.16.0)
Requires-Dist: python-heatclient (==1.17.0)
Requires-Dist: python-keystoneclient (==3.19.0)
Requires-Dist: python-neutronclient (==6.12.0)
Requires-Dist: python-novaclient (==14.0.0)
Requires-Dist: python-openstackclient (==3.18.0)
Requires-Dist: python-swiftclient (==3.7.0)
